.DS_Store
influence/__init__.py
influence/cin.py
influence/cout.py
influence/array/__init__.py
influence/array/arrays.py
influence/array/multiarray.py
influence/dict/__init__.py
influence/dict/idict.py
influence/dict/treemap.py
influence/extender/__init__.py
influence/extender/cin/__init__.py
influence/extender/cin/input.py
influence/extender/cout/__init__.py
influence/extender/cout/printer.py
influence/extender/list/__init__.py
influence/extender/list/aslist.py
influence/extender/list/multilist.py
influence/extender/list/ragged.py
influence/extender/math/__init__.py
influence/extender/math/const.py
influence/extender/math/cos.py
influence/extender/math/frac.py
influence/extender/math/mixednum.py
influence/extender/math/stats.py
influence/extender/math/agrapher/__init__.py
influence/extender/math/agrapher/asyncgrapher.py
influence/extender/math/grapher/__init__.py
influence/extender/math/grapher/grapher.py
influence/extender/string/__init__.py
influence/extender/string/aslist.py
influence/extender/string/subtract.py
influence/list/__init__.py
influence/list/aslist.py
influence/list/multilist.py
influence/list/ragged.py
influence/list/stack.py
influence/math/__init__.py
influence/math/asyncgrapher.py
influence/math/const.py
influence/math/cos.py
influence/math/frac.py
influence/math/grapher.py
influence/math/mixednum.py
influence/math/stats.py
influence/math/stemandleaf.py
influence/set/__init__.py
influence/set/treeset.py
influence/string/__init__.py
influence/string/aslist.py
influence/string/stringbuffer.py
influence/string/subtract.py
influence/upgrader/__init__.py
influence/upgrader/array/__init__.py
influence/upgrader/array/arrays.py
influence/upgrader/array/multiarray.py
influence-1.1.dist-info/LICENSE.txt
influence-1.1.dist-info/METADATA
influence-1.1.dist-info/WHEEL
influence-1.1.dist-info/top_level.txt
influence-1.1.dist-info/RECORD
