Metadata-Version: 2.1
Name: influence
Version: 1.1
Summary: A utility package influenced by java, coded in python
Home-page: https://github.com/RandomKiddo/influence
Author: Neil
Author-email: nghugare2@outlook.com
License: MIT
Download-URL: https://github.com/RandomKiddo/influence/archive/v1.1.tar.gz
Keywords: PYTHON,EXTENDER,UPGRADER
Platform: UNKNOWN
Classifier: Development Status :: 3 - Alpha
Classifier: Intended Audience :: Developers
Classifier: Topic :: Software Development :: Build Tools
Classifier: License :: OSI Approved :: MIT License
Classifier: Programming Language :: Python :: 3
Classifier: Programming Language :: Python :: 3.8
